__init__.py
__main__.py
actions.py
cube.py
cube_runtime.py
orientation.py
parser.py
pattern.py
scrambler.py
sides.py
cli/__init__.py
cli/cube_builder.py
cli/entry.py
cli/error_display.py
cli/options.py
cli/postprocessors_builder.py
compiler/__init__.py
compiler/code_map.py
compiler/codeio.py
compiler/errors.py
compiler/expression.py
compiler/operators.py
compiler/parser.py
compiler/stack.py
compiler/types.py
cubelang/__init__.py
cubelang/__main__.py
cubelang/actions.py
cubelang/cube.py
cubelang/cube_runtime.py
cubelang/orientation.py
cubelang/parser.py
cubelang/pattern.py
cubelang/scrambler.py
cubelang/sides.py
cubelang/cli/__init__.py
cubelang/cli/cube_builder.py
cubelang/cli/entry.py
cubelang/cli/error_display.py
cubelang/cli/options.py
cubelang/cli/postprocessors_builder.py
cubelang/compiler/__init__.py
cubelang/compiler/code_map.py
cubelang/compiler/codeio.py
cubelang/compiler/errors.py
cubelang/compiler/expression.py
cubelang/compiler/operators.py
cubelang/compiler/parser.py
cubelang/compiler/stack.py
cubelang/compiler/types.py
cubelang/data/syntax.lark
cubelang/execution/__init__.py
cubelang/execution/executor.py
cubelang/execution/rt_error.py
cubelang/execution/rt_function.py
cubelang/postprocessing/__init__.py
cubelang/postprocessing/base.py
cubelang/postprocessing/formatter.py
cubelang/postprocessing/optimizer.py
cubelang/postprocessing/orientation_freezer.py
cubelang/stdlib/__init__.py
cubelang/stdlib/collections.py
cubelang/stdlib/math.py
data/syntax.lark
execution/__init__.py
execution/executor.py
execution/rt_error.py
execution/rt_function.py
libcube/__init__.py
libcube/__main__.py
libcube/actions.py
libcube/cube.py
libcube/cube_runtime.py
libcube/orientation.py
libcube/parser.py
libcube/pattern.py
libcube/scrambler.py
libcube/sides.py
libcube/cli/__init__.py
libcube/cli/cube_builder.py
libcube/cli/entry.py
libcube/cli/error_display.py
libcube/cli/options.py
libcube/cli/postprocessors_builder.py
libcube/compiler/__init__.py
libcube/compiler/code_map.py
libcube.egg-info/PKG-INFO
libcube.egg-info/SOURCES.txt
libcube.egg-info/dependency_links.txt
libcube.egg-info/entry_points.txt
libcube.egg-info/requires.txt
libcube.egg-info/top_level.txt
CubeLang-0.1.4.dist-info/LICENSE
CubeLang-0.1.4.dist-info/LICENSE-3RD-PARTY
CubeLang-0.1.4.dist-info/METADATA
CubeLang-0.1.4.dist-info/WHEEL
CubeLang-0.1.4.dist-info/entry_points.txt
CubeLang-0.1.4.dist-info/top_level.txt
CubeLang-0.1.4.dist-info/RECORD
