Metadata-Version: 2.1
Name: CubeLang
Version: 0.1.4
Summary: Domain-specific programming language made for solving twisting cube puzzles
Home-page: https://github.com/poletaevvlad/CubeLang
Author: 0.1.4
Author-email: poletaev.vladislav@gmail.com
License: MIT
Platform: UNKNOWN
Classifier: Environment :: Console
Classifier: Intended Audience :: Developers
Classifier: Intended Audience :: Other Audience
Classifier: License :: OSI Approved :: MIT License
Classifier: Natural Language :: English
Classifier: Programming Language :: Python
Classifier: Programming Language :: Python :: 3 :: Only
Classifier: Programming Language :: Python :: 3.6
Classifier: Programming Language :: Python :: 3.7
Classifier: Programming Language :: Python :: 3.8
Classifier: Topic :: Games/Entertainment :: Puzzle Games
Requires-Dist: lark-parser
Requires-Dist: termcolor
